{"id":7,"userId":1,"uuid":"883dd363-f832-4c6a-8681-0dffc8ab638a","version":3,"name":"Transaction Dataset","description":"Retail Transactions Datset","header":true,"path":"data/transaction.csv","delimiter":",","datasetType":"CSV","filterLinesContaining":"purchasequantity","datasetSchema":"{colNames:[\"id\",\"chain\",\"dept\",\"category\",\"company\",\"brand\",\"date\",\"productsize\",\"productmeasure\",\"purchasequantity\",\"purchaseamount\"],colTypes:[\"INTEGER\",\"INTEGER\",\"INTEGER\",\"INTEGER\",\"INTEGER\",\"INTEGER\",\"STRING\",\"DOUBLE\",\"STRING\",\"INTEGER\",\"DOUBLE\"],colMLTypes:[\"NUMERIC\",\"NUMERIC\",\"NUMERIC\",\"NUMERIC\",\"NUMERIC\",\"NUMERIC\",\"TEXT\",\"NUMERIC\",\"TEXT\",\"NUMERIC\",\"NUMERIC\"]}","dateCreated":"Sep 16, 2018 12:20:18 PM","dateLastUpdated":"Sep 16, 2018 12:20:18 PM","projectId":1}